orgpedia_cabsec/__init__.py
orgpedia_cabsec/data.zip
orgpedia_cabsec/datapackage.json
orgpedia_cabsec-0.0.12.dist-info/LICENSE.txt
orgpedia_cabsec-0.0.12.dist-info/METADATA
orgpedia_cabsec-0.0.12.dist-info/WHEEL
orgpedia_cabsec-0.0.12.dist-info/RECORD
