Metadata-Version: 2.1
Name: orgpedia-cabsec
Version: 0.0.12
Summary: Datapackage containing orders of Cabinet Secretariat from https://cabsec.gov.in/.
License: MIT
Keywords: information extraction,data package,government data
Author: Orgpedia Foundation
Author-email: orgpedia.foundation@gmail.com
Requires-Python: >3.8.1,<4.0
Classifier: Development Status :: 2 - Pre-Alpha
Classifier: Intended Audience :: Developers
Classifier: License :: OSI Approved :: MIT License
Classifier: Natural Language :: English
Classifier: Programming Language :: Python :: 3
Classifier: Programming Language :: Python :: 3.9
Classifier: Programming Language :: Python :: 3.10
Classifier: Programming Language :: Python :: 3.11
Classifier: Programming Language :: Python :: 3.12
Classifier: Programming Language :: Python :: 3.8
Classifier: Topic :: Scientific/Engineering :: Artificial Intelligence
Classifier: Topic :: Scientific/Engineering :: Image Processing
Classifier: Topic :: Scientific/Engineering :: Image Recognition
Classifier: Topic :: Scientific/Engineering :: Information Analysis
Classifier: Topic :: Scientific/Engineering :: Visualization
Requires-Dist: google-cloud-storage (>=2.15.0,<3.0.0)
Requires-Dist: google-cloud-vision (>=3.7.2,<4.0.0)
Requires-Dist: numpy
Requires-Dist: transformers[torch] (>=4.38.2,<5.0.0)
Requires-Dist: waybackpy (>=3.0.6,<4.0.0)
Project-URL: data issues, https://github.com/orgpedia/cabsec/discussions
Project-URL: homepage, https://www.orgpedia.in/
Project-URL: repository, https://github.com/orgpedia/cabsec
